Metadata-Version: 2.1
Name: wbxSearch
Version: 0.1.1
Summary: Удобный инструмент для работы с выдачами
Home-page: https://github.com/ZhuravlevDmi/wbxSearch
Author: ZhuravlevDmi
Author-email: Dima15129@gmail.com
License: Apache License, version 2.0, see LICENSE file
Download-URL: https://github.com/ZhuravlevDmi/wbxSearch/archive/v0.1.1.zip
Platform: UNKNOWN
Classifier: License :: OSI Approved :: Apache Software License
Classifier: Intended Audience :: Developers
Classifier: Operating System :: OS Independent
Classifier: Programming Language :: Python
Classifier: Programming Language :: Python :: 3.10
Classifier: Programming Language :: Python :: 3 :: Only
Classifier: Programming Language :: Python :: Implementation :: PyPy
Classifier: Programming Language :: Python :: Implementation :: CPython
License-File: LICENSE
